README.md
setup.py
elefas/__init__.py
elefas.egg-info/PKG-INFO
elefas.egg-info/SOURCES.txt
elefas.egg-info/dependency_links.txt
elefas.egg-info/requires.txt
elefas.egg-info/top_level.txt
elefas/engine/__init__.py
elefas/engine/hyper_pointer.py
elefas/engine/scores.py
elefas/engine/utils.py
elefas/hyperparameters/__init__.py
elefas/hyperparameters/base_hyper.py
elefas/hyperparameters/choice.py
elefas/hyperparameters/constraint.py
elefas/hyperparameters/dependent.py
elefas/hyperparameters/numeric.py
elefas/spaces/__init__.py
elefas/spaces/grid_search.py
elefas/spaces/random_search.py
elefas/spaces/search.py
elefas/spaces/sobol_search.py