Metadata-Version: 1.2
Name: elefas
Version: 0.1.10
Summary: Friendly hyperparameter optimization 
Home-page: https://github.com/mjmikulski/elefas
Author: Maciej Mikulski
Author-email: maciej.mikulski@doctoral.uj.edu.pl
License: MIT
Keywords: hyperparameters optimization
Platform: UNKNOWN
Classifier: Development Status :: 3 - Alpha
Classifier: Intended Audience :: Science/Research
Classifier: License :: OSI Approved :: MIT License
Classifier: Programming Language :: Python :: 3.6
Classifier: Topic :: Software Development :: Libraries
Classifier: Topic :: Software Development :: Libraries :: Python Modules
Requires-Python: ~=3.6
